Workbook

Sheet Hoja1
A1: ItemCode | C1: UserText
A2: ItemCode | C2: UserText
A3: 5.4023 | B3: =VLOOKUP(A3,'equiv ant y nuevo'!$A$2:$B$1931,2,FALSE) -> #N/A | C3: 5. 4023 (PLG 00044) Plug DC Sony 1,7 Fino *Plástico con Punta Amarilla *Se usa en Discman/Walkman
A4: 209 | B4: =VLOOKUP(A4,'equiv ant y nuevo'!$A$2:$B$1931,2,FALSE) -> #N/A | C4: CUERDA PRIMERA P/GUITARRA ELEC. 9 BLUE STEEL Especificaciones: - SERIE: BLUE STEEL - CALIBRE: NUMERO 9 (0.23MM) PRIMERA CUERDA - PARA GUITARRA ELECTRICA Y ACUSTICA
A5: 1009 | B5: =VLOOKUP(A5,'equiv ant y nuevo'!$A$2:$B$1931,2,FALSE) -> #N/A | C5: CUERDA PRIMERA P/GUITARRA ELEC. 9 Especificaciones: - MATERIAL: ACERO LISO - CALIBRE: NUMERO 9 (0.23MM) PRIMERA CUERDA - PARA GUITARRA ELECTRICA Y ACUSTICA
A6: 1010 | B6: =VLOOKUP(A6,'equiv ant y nuevo'!$A$2:$B$1931,2,FALSE) -> #N/A | C6: CUERDA PRIMERA P/GUITARRA ELEC. 10 Especificaciones: - MATERIAL: ACERO LISO - CALIBRE: NUMERO 10 (0.25MM) PRIMERA CUERDA - PARA GUITARRA ELECTRICA Y ACUSTICA
A7: 1011 | B7: =VLOOKUP(A7,'equiv ant y nuevo'!$A$2:$B$1931,2,FALSE) -> #N/A | C7: CUERDA SEGUNDA P/GUITARRA ELEC. 11 Especificaciones: - MATERIAL: ACERO LISO - CALIBRE: NUMERO 11 (0.28MM) SEGUNDA CUERDA - PARA GUITARRA ELECTRICA Y ACUSTICA
A8: 1016 | B8: =VLOOKUP(A8,'equiv ant y nuevo'!$A$2:$B$1931,2,FALSE) -> #N/A | C8: CUERDA TERCERA P/GUITARRA ELEC. 16 Especificaciones: - MATERIAL: ACERO LISO - CALIBRE: NUMERO 16 (0.41MM) TERCERA CUERDA - PARA GUITARRA ELECTRICA Y ACUSTICA
A9: 1017 | B9: =VLOOKUP(A9,'equiv ant y nuevo'!$A$2:$B$1931,2,FALSE) -> #N/A | C9: CUERDA TERCERA DE GUITARRA ELECTRICA #17 Especificaciones: - Calibre .017 - Serie signature - Hecho en estados unidos con acero niquelado
A10: 1124 | B10: =VLOOKUP(A10,'equiv ant y nuevo'!$A$2:$B$1931,2,FALSE) -> #N/A | C10: CUERDA CUARTA DE GUITARRA ELECTRICA #24 Especificaciones: - Calibre .024 - Serie signature - Hecho en estados unidos con acero niquelado
A11: 1126 | B11: =VLOOKUP(A11,'equiv ant y nuevo'!$A$2:$B$1931,2,FALSE) -> #N/A | C11: CUERDA CUARTA DE GUITARRA ELECTRICA #26 Especificaciones: - Calibre .026 - Serie signature - Hecho en estados unidos con acero niquelado
A12: 1136 | B12: =VLOOKUP(A12,'equiv ant y nuevo'!$A$2:$B$1931,2,FALSE) -> #N/A | C12: CUERDA QUINTA P/GUITARRA ELEC. 36 Especificaciones: - MATERIAL: ACERO LISO NPS WOUND - CALIBRE: NUMERO 36 (0.91MM) QUINTA CUERDA - PARA GUITARRA ELECTRICA
A13: 1146 | B13: =VLOOKUP(A13,'equiv ant y nuevo'!$A$2:$B$1931,2,FALSE) -> #N/A | C13: CUERDA SEXTA P/GUITARRA ELEC. 46 Especificaciones: - MATERIAL: ACERO LISO NPS WOUND - CALIBRE: NUMERO 46 (1.17MM) SEXTA CUERDA - PARA GUITARRA ELECTRICA
A14: 1224 | B14: =VLOOKUP(A14,'equiv ant y nuevo'!$A$2:$B$1931,2,FALSE) -> #N/A | C14: CUERDA TERCERA DE GUITARRA ACUSTICA #24 Especificaciones: - Calibre .024 - Serie vintage bronze - Hecho en estados unidos con 85% de cobre y 15% zinc
... A91: 4780861 | B91: =VLOOKUP(A91,'equiv ant y nuevo'!$A$2:$B$1931,2,FALSE) -> #N/A | C91: CONTROLADOR 2 CH DJCONTROL INSTINCT P8_x000D_ _x000D_ Descripcion:_x000D_ _x000D_ - Controlador hércules doble deck_x000D_ - 8 pads de sample multicolor_x000D_ - Sync , cue, play, pause _x000D_ - Deck sensible al tacto y scratch_x000D_ - Ecualizador de tres bandas, 2 fader de volumen y crossfader, SHIFT_x000D_ - Tarjeta de sonido integrada 24 bit con 2 salidas RCA, salida mini Jack estéreo 3.5 _x000D_ para audífonos_x000D_ - Cable de USB desmontable
A92: 0.22MF-100V | B92: =VLOOKUP(A92,'equiv ant y nuevo'!$A$2:$B$1931,2,FALSE) -> #N/A | C92: FILTRO 105°
A93: 0.47MF-100V | B93: =VLOOKUP(A93,'equiv ant y nuevo'!$A$2:$B$1931,2,FALSE) -> #N/A | C93: FILTRO 105°
A94: 0.47MF-160V | B94: =VLOOKUP(A94,'equiv ant y nuevo'!$A$2:$B$1931,2,FALSE) -> #N/A | C94: FILTRO 105°
A95: 0.47MF-50V | B95: =VLOOKUP(A95,'equiv ant y nuevo'!$A$2:$B$1931,2,FALSE) -> #N/A | C95: FILTRO 105°
A96: 00104C | B96: =VLOOKUP(A96,'equiv ant y nuevo'!$A$2:$B$1931,2,FALSE) -> #N/A | C96: CONTROL REMOTO P/TV
A97: 00478800XUND | B97: =VLOOKUP(A97,'equiv ant y nuevo'!$A$2:$B$1931,2,FALSE) -> #N/A | C97: UNETA THUMB 371 NEGRO X UNIDAD
A98: 00478810XUND | B98: =VLOOKUP(A98,'equiv ant y nuevo'!$A$2:$B$1931,2,FALSE) -> #N/A | C98: UNETA THUMB 371 BLANCO X UNIDAD
A99: 00479470XUND | B99: =VLOOKUP(A99,'equiv ant y nuevo'!$A$2:$B$1931,2,FALSE) -> #N/A | C99: VITELA DREAMERS 351 ROJO 0.50MM X UNIDAD
A100: 00479480XUND | B100: =VLOOKUP(A100,'equiv ant y nuevo'!$A$2:$B$1931,2,FALSE) -> #N/A | C100: VITELA DREAMERS 351 NARANJA 0.60MM X UNIDAD
A101: 00479490XUND | B101: =VLOOKUP(A101,'equiv ant y nuevo'!$A$2:$B$1931,2,FALSE) -> #N/A | C101: VITELA DREAMERS 351 AMARILLO 0.73MM X UNIDAD
A102: 00479500XUND | B102: =VLOOKUP(A102,'equiv ant y nuevo'!$A$2:$B$1931,2,FALSE) -> #N/A | C102: VITELA DREAMERS 351 VERDE 0.88MM X UNIDAD
A103: 00479540XUND | B103: =VLOOKUP(A103,'equiv ant y nuevo'!$A$2:$B$1931,2,FALSE) -> #N/A | C103: VITELA ABALONE 351 0.50MM X UNIDAD
... A8010: ZYE-005 OF | B8010: =VLOOKUP(A8010,'equiv ant y nuevo'!$A$2:$B$1931,2,FALSE) -> #N/A | C8010: LUZ LED SMALL MUSHROOM Especificaciones: - Tipo de luz: led RGB (5mm) - Colores: verde, azul, rojo, blanco - Potencia: 20W - Voltaje: 110Vac 60Hz - Modos de funcionamiento: Automático, DMX, maestro/esclavo - Posee 54 diodos led y 15 lentes Observaciones: - Programación mediante DIP-SWITCH - Velocidad variable, flash - Funciones y programación en manual adjunto

Sheet equiv ant y nuevo
A1: anterior | B1: ItemCode
A2: 24C04 | B2: 24C04 CLD CLA
A3: KBZ02561 | B3: 24C08 CLA
A4: KBZ02566 | B4: 2N2222 CLA
A5: KBZ00146 | B5: 2N2647 CLA
A6: KBZ02451 | B6: 2N3904 CLA
A7: KBZ02470 | B7: 2N3906 CLA
A8: KBZ02556 | B8: 2N5401 CLA
A9: 2N5551 | B9: 2N5551 CLA
A10: 2SA1013 | B10: 2SA1013 CLA
A11: 2SA1170 CLA | B11: 2SA1170 CLA
A12: TRS00029 | B12: 2SA1266Y CLA
... A65: TRS02322 | B65: 2SD37 CLA
B66: 2SD601 SEMI-CLD CLA
B67: 2SD633 SEMI-CLD CLA
A68: KBZ00342 | B68: 2SD669 CLA
B69: 2SD859 SEMI-CLD CLA
A70: 2SK1102 CLA | B70: 2SK1102 CLA
A71: 2SK2434 SMD CLA | B71: 2SK2434 SMD CLA
A72: KBZ00314 | B72: 2SK2564 CLA
A73: KBZ02452 | B73: 47MF-16V CLA
A74: KBZ00306 | B74: 5Q0765RT CLA
A75: KBZ00315 | B75: 5Q1265RF CLA
A76: KBZ02151 | B76: 680MF-16V CLA
A77: KBZ02152 | B77: 680MF-25V CLA
A78: 74LS00 | B78: 74LS00 CLA
A79: 74LS02 | B79: 74LS02 CLA
A80: KBZ02541 | B80: 74LS04 CLA
A81: KBZ02508 | B81: 74LS08 CLA
... A113: KBZ02458 | B113: AD-12V 5A CLA
B114: AD-E95100LU-P1-OP1 CLA
A115: PA-150 | B115: PA-150 CLA
A116: ADAP107-ECO | B116: AD-12V 2A CLA
A117: KBZ00454 | B117: AD-5V 2A CLA
A118: HCD-600 CLA | B118: HCD-600 CLA
B119: AD-G1XON CLA
A120: KBZ02322 | B120: AD-INT-2.5 12V 2A CLA
A121: KBZ02485 | B121: AD-INT-2.1 12V 2A CLA
A122: KBZ02323 | B122: AD-INT-2.1 5V 2A CLA
A123: KBZ02335 | B123: AD-INT-2.5 6V 2A CLA
A124: KBZ02468 | B124: AD-6PL 12V 2A CLA
A125: KBZ02326 | B125: AD-19V 3.42A CLA
A126: KBZ02462 | B126: AD-19V 2.15A CLA
A127: KBZ02407 | B127: AD-19V 2.1A CLA
A128: KBZ02325 | B128: AD-19V 3.34A CLA
A129: KBZ02363 | B129: AD-19.5V 4.62A CLA
A130: KBZ02365 | B130: AD-19.5V 4.62A HP CLA
A131: KBZ02019 | B131: AD-19V 4.74A CLA
A132: KBZ02518 | B132: AD-20V 4.5A CLA
B133: AD-19V 1.58A CLA
A134: KBZ02409 | B134: AD-19V 1.58A DELL CLA
A135: KBZ02361 | B135: AD-19V 4.74A CLA
A136: KBZ02362 | B136: AD-19V 2.1A SAM CLA
A137: KBZ02408 | B137: AD-19.5V 3.05A CLA
A138: KBZ02364 | B138: AD-19.5V 4.7A CLA
A139: KBZ02327 | B139: AD-15V 6A CLA
A140: KBZ02446 | B140: AD-19V 3.42A CLA
A141: KBZ02403 | B141: AD-19V 4.74A TOSH CLA
A142: KBZ02079 | B142: AD-12V 3A CLA
A143: KBZ02224 | B143: AD-19V 2.1A LG CLA
A144: KBZ02278 | B144: AD-14V 2.1A CLA
A145: AD-E95100LG-P2 CLA | B145: AD-E95100LG-P2 CLA
B146: PA-300C CLA
B147: PA-3C CLA
B148: PA-5D CLA
A149: KBZ02287 | B149: AD-96W CLA
A150: AD-A12150LW | B150: AD-A12150LW CLA
A151: KBZ02003 | B151: AD-ID-SAT CLA
A152: KBZ00250 | B152: AD-LAPTOP CLA
A153: KBZ00411 | B153: AD-18.5V 3.5A CLA
A154: KBZ02514 | B154: AD-20V 4.5A LEN CLA
A155: KBZ00404 | B155: AD-LAP-UNI CLA
A156: CAR-MP3ALS806 | B156: AD-CAR CLA
A157: CAR-MP3-A809 | B157: AD-CAR GR CLA
A158: CAR-MP3-A807 | B158: AD-CAR BK CLA
A159: KBZ02103 | B159: AD-2.0-LAN CLA
A160: KBZ00383 | B160: JP1081 CLA
... A167: KBZ02492 | B167: AD-DVIxVGA 24_5 CLA
B168: AD-19.5V-1.58A CLA
A169: KBZ02466 | B169: AD-19V 1.58A HP CLA
A170: KBZ02465 | B170: AD-19.5V 2.1A CLA
A171: KBZ02463 | B171: AD-19V 2.1A SONY CLA
A172: TU-CSLH CLA | B172: TU-CSLH CLA
A173: CS-260 CLA | B173: CS-260 CLA
A174: TU-GBBKH CLA | B174: TU-GBBKH CLA
A175: CS-620 CLA | B175: CS-620 CLA
A176: CTU-C2 CLA | B176: CTU-C2 CLA
A177: KBZ02063 | B177: AG-DISC CLA
A178: KBZ00560 | B178: AL-8M-0.1MM CLA
A179: KBZ00384 | B179: SCT-2520 BK CLA
A180: KBZ02064 | B180: AMP-0-30A CLA
B181: CHAMPION20 CLA
B182: CHAMPION40 CLA
A183: MB60 CLA | B183: MB60 CLA
A184: MB150 CLA | B184: MB150 CLA
A185: MG101CFX CLA | B185: MG101CFX CLA
B186: MG102CFX CLA
A187: MG15FX CLA | B187: MG15FX CLA
A188: MG15CF CLA | B188: MG15CFX CLA
A189: MG30CFX CLA | B189: MG30CFX CLA
...
